[{"name": "Grady1", "id": 1, "password": "recommender", "age": 34, "vote": "right"}, {"name": "Charles2", "id": 2, "password": "recommender", "age": 30, "vote": "centre"}, {"name": "John3", "id": 3, "password": "recommender", "age": 24, "vote": "left"}, {"name": "Jennifer4", "id": 4, "password": "recommender", "age": 26, "vote": "right"}, {"name": "Elizabeth5", "id": 5, "password": "recommender", "age": 27, "vote": "left"}, {"name": "Adam6", "id": 6, "password": "recommender", "age": 29, "vote": "left"}, {"name": "Jean7", "id": 7, "password": "recommender", "age": 34, "vote": "right"}, {"name": "Jean8", "id": 8, "password": "recommender", "age": 24, "vote": "centre"}, {"name": "Marvin9", "id": 9, "password": "recommender", "age": 29, "vote": "right"}, {"name": "Tricia10", "id": 10, "password": "recommender", "age": 25, "vote": "centre"}, {"name": "Mary11", "id": 11, "password": "recommender", "age": 29, "vote": "centre"}, {"name": "Diego12", "id": 12, "password": "recommender", "age": 22, "vote": "left"}, {"name": "Lisa13", "id": 13, "password": "recommender", "age": 27, "vote": "centre"}, {"name": "Israel14", "id": 14, "password": "recommender", "age": 23, "vote": "left"}, {"name": "Douglas15", "id": 15, "password": "recommender", "age": 28, "vote": "centre"}, {"name": "Mary16", "id": 16, "password": "recommender", "age": 22, "vote": "centre"}, {"name": "Adam17", "id": 17, "password": "recommender", "age": 27, "vote": "left"}, {"name": "Mary18", "id": 18, "password": "recommender", "age": 22, "vote": "centre"}, {"name": "Jerald19", "id": 19, "password": "recommender", "age": 20, "vote": "centre"}, {"name": "Barbara20", "id": 20, "password": "recommender", "age": 32, "vote": "left"}, {"name": "Ray21", "id": 21, "password": "recommender", "age": 21, "vote": "right"}, {"name": "Joan22", "id": 22, "password": "recommender", "age": 28, "vote": "centre"}, {"name": "Ronald23", "id": 23, "password": "recommender", "age": 24, "vote": "centre"}, {"name": "Jeffrey24", "id": 24, "password": "recommender", "age": 27, "vote": "left"}, {"name": "Viola25", "id": 25, "password": "recommender", "age": 32, "vote": "left"}, {"name": "Susie26", "id": 26, "password": "recommender", "age": 22, "vote": "centre"}, {"name": "James27", "id": 27, "password": "recommender", "age": 28, "vote": "centre"}, {"name": "Stephen28", "id": 28, "password": "recommender", "age": 22, "vote": "centre"}, {"name": "Zella29", "id": 29, "password": "recommender", "age": 23, "vote": "right"}, {"name": "Glenn30", "id": 30, "password": "recommender", "age": 25, "vote": "left"}, {"name": "Queen31", "id": 31, "password": "recommender", "age": 30, "vote": "left"}, {"name": "Dianna32", "id": 32, "password": "recommender", "age": 28, "vote": "centre"}, {"name": "Edwin33", "id": 33, "password": "recommender", "age": 34, "vote": "right"}, {"name": "Ronald34", "id": 34, "password": "recommender", "age": 27, "vote": "left"}, {"name": "Mark35", "id": 35, "password": "recommender", "age": 26, "vote": "left"}, {"name": "George36", "id": 36, "password": "recommender", "age": 24, "vote": "left"}, {"name": "Eric37", "id": 37, "password": "recommender", "age": 27, "vote": "centre"}, {"name": "Patricia38", "id": 38, "password": "recommender", "age": 24, "vote": "left"}, {"name": "Glennis39", "id": 39, "password": "recommender", "age": 25, "vote": "left"}, {"name": "Robert40", "id": 40, "password": "recommender", "age": 22, "vote": "left"}, {"name": "John41", "id": 41, "password": "recommender", "age": 22, "vote": "centre"}, {"name": "Nicholas42", "id": 42, "password": "recommender", "age": 28, "vote": "centre"}, {"name": "Elizabeth43", "id": 43, "password": "recommender", "age": 34, "vote": "left"}, {"name": "Jan44", "id": 44, "password": "recommender", "age": 31, "vote": "left"}, {"name": "Ronnie45", "id": 45, "password": "recommender", "age": 51, "vote": "centre"}, {"name": "Richard46", "id": 46, "password": "recommender", "age": 50, "vote": "left"}, {"name": "Manuel47", "id": 47, "password": "recommender", "age": 51, "vote": "left"}, {"name": "Alissa48", "id": 48, "password": "recommender", "age": 42, "vote": "right"}, {"name": "Joey49", "id": 49, "password": "recommender", "age": 43, "vote": "right"}, {"name": "John50", "id": 50, "password": "recommender", "age": 52, "vote": "centre"}, {"name": "James51", "id": 51, "password": "recommender", "age": 47, "vote": "right"}, {"name": "Andrew52", "id": 52, "password": "recommender", "age": 45, "vote": "right"}, {"name": "Cassy53", "id": 53, "password": "recommender", "age": 42, "vote": "right"}, {"name": "Charles54", "id": 54, "password": "recommender", "age": 47, "vote": "right"}, {"name": "Yolanda55", "id": 55, "password": "recommender", "age": 38, "vote": "centre"}, {"name": "Gregory56", "id": 56, "password": "recommender", "age": 49, "vote": "right"}, {"name": "Mary57", "id": 57, "password": "recommender", "age": 54, "vote": "centre"}, {"name": "Williams58", "id": 58, "password": "recommender", "age": 41, "vote": "centre"}, {"name": "Tasha59", "id": 59, "password": "recommender", "age": 47, "vote": "left"}, {"name": "Robert60", "id": 60, "password": "recommender", "age": 40, "vote": "right"}, {"name": "Margaret61", "id": 61, "password": "recommender", "age": 43, "vote": "right"}, {"name": "Josie62", "id": 62, "password": "recommender", "age": 49, "vote": "left"}, {"name": "Clarice63", "id": 63, "password": "recommender", "age": 49, "vote": "centre"}, {"name": "Patrick64", "id": 64, "password": "recommender", "age": 46, "vote": "left"}, {"name": "Eleanor65", "id": 65, "password": "recommender", "age": 43, "vote": "left"}, {"name": "Joseph66", "id": 66, "password": "recommender", "age": 48, "vote": "right"}, {"name": "Norman67", "id": 67, "password": "recommender", "age": 35, "vote": "centre"}, {"name": "David68", "id": 68, "password": "recommender", "age": 35, "vote": "right"}, {"name": "Melissa69", "id": 69, "password": "recommender", "age": 46, "vote": "right"}, {"name": "Ciara70", "id": 70, "password": "recommender", "age": 35, "vote": "left"}, {"name": "Orlando71", "id": 71, "password": "recommender", "age": 37, "vote": "centre"}, {"name": "George72", "id": 72, "password": "recommender", "age": 42, "vote": "centre"}, {"name": "Richard73", "id": 73, "password": "recommender", "age": 36, "vote": "right"}, {"name": "Kelly74", "id": 74, "password": "recommender", "age": 44, "vote": "left"}, {"name": "John75", "id": 75, "password": "recommender", "age": 41, "vote": "centre"}, {"name": "Natalie76", "id": 76, "password": "recommender", "age": 36, "vote": "left"}, {"name": "Barbara77", "id": 77, "password": "recommender", "age": 51, "vote": "right"}, {"name": "William78", "id": 78, "password": "recommender", "age": 50, "vote": "left"}, {"name": "Joyce79", "id": 79, "password": "recommender", "age": 54, "vote": "centre"}, {"name": "Daniel80", "id": 80, "password": "recommender", "age": 38, "vote": "centre"}, {"name": "Jeffrey81", "id": 81, "password": "recommender", "age": 48, "vote": "right"}, {"name": "Phillip82", "id": 82, "password": "recommender", "age": 44, "vote": "left"}, {"name": "Derek83", "id": 83, "password": "recommender", "age": 52, "vote": "centre"}, {"name": "James84", "id": 84, "password": "recommender", "age": 67, "vote": "right"}, {"name": "Melinda85", "id": 85, "password": "recommender", "age": 56, "vote": "right"}, {"name": "Nancy86", "id": 86, "password": "recommender", "age": 65, "vote": "left"}, {"name": "Delia87", "id": 87, "password": "recommender", "age": 56, "vote": "right"}, {"name": "Sarah88", "id": 88, "password": "recommender", "age": 65, "vote": "right"}, {"name": "Jerrod89", "id": 89, "password": "recommender", "age": 70, "vote": "right"}, {"name": "Lena90", "id": 90, "password": "recommender", "age": 65, "vote": "centre"}, {"name": "Chang91", "id": 91, "password": "recommender", "age": 59, "vote": "right"}, {"name": "Elizabeth92", "id": 92, "password": "recommender", "age": 58, "vote": "right"}, {"name": "Brian93", "id": 93, "password": "recommender", "age": 56, "vote": "left"}, {"name": "Louis94", "id": 94, "password": "recommender", "age": 56, "vote": "left"}, {"name": "April95", "id": 95, "password": "recommender", "age": 63, "vote": "centre"}, {"name": "Edwin96", "id": 96, "password": "recommender", "age": 65, "vote": "left"}, {"name": "Hazel97", "id": 97, "password": "recommender", "age": 66, "vote": "centre"}, {"name": "Sara98", "id": 98, "password": "recommender", "age": 61, "vote": "centre"}, {"name": "Sherry99", "id": 99, "password": "recommender", "age": 69, "vote": "centre"}, {"name": "Dorothy100", "id": 100, "password": "recommender", "age": 62, "vote": "right"}]